my_main_manager/__init__.py
my_main_manager/manager.py
my_main_manager-1.0.12.dist-info/METADATA
my_main_manager-1.0.12.dist-info/WHEEL
my_main_manager-1.0.12.dist-info/top_level.txt
my_main_manager-1.0.12.dist-info/RECORD
