Metadata-Version: 2.1
Name: my_main_manager
Version: 1.0.12
Summary: A Python package for managing hidden services.
Home-page: https://github.com/yesjdnke/manager
Author: yesjdnke
Author-email: goaway@gmail.com
Classifier: Programming Language :: Python :: 3
Classifier: License :: OSI Approved :: MIT License
Classifier: Operating System :: OS Independent
Requires-Python: >=3.6
